pyUML/Association.py
pyUML/Graph.py
pyUML/UMLClass.py
pyUML/__init__.py
pyUML-0.1.0a0.dist-info/LICENSE
pyUML-0.1.0a0.dist-info/METADATA
pyUML-0.1.0a0.dist-info/WHEEL
pyUML-0.1.0a0.dist-info/top_level.txt
pyUML-0.1.0a0.dist-info/RECORD
