Metadata-Version: 2.1
Name: pyUML
Version: 0.1.0a0
Summary: Create simple GraphViz DOT UML graphs with a python script
Home-page: https://githib.com/trevismd/pyUML
Author: Florian Charlier
Author-email: florian.charlier@cascliniques.be
License: GNU GPLv3
Platform: UNKNOWN
Classifier: Programming Language :: Python :: 3
Classifier: License :: OSI Approved :: GNU General Public License v3 (GPLv3)
Classifier: Operating System :: OS Independent
Classifier: Development Status :: 3 - Alpha
License-File: LICENSE
